Metadata-Version: 1.1
Name: django-collectdir
Version: 1.0.0
Summary: Generic purpose collecstatic alternative, with lovely colors
Home-page: https://git.yourlabs.org/oss/django-collectdir
Author: James Pic
Author-email: jamespic@gmail.com
License: MIT
Keywords: django
Platform: UNKNOWN
Classifier: Development Status :: 1 - Planning
Classifier: Environment :: Web Environment
Classifier: Framework :: Django
Classifier: Intended Audience :: Developers
Classifier: License :: OSI Approved :: MIT License
Classifier: Operating System :: OS Independent
Classifier: Programming Language :: Python
Classifier: Programming Language :: Python :: 3
Classifier: Topic :: Internet :: WWW/HTTP
Classifier: Topic :: Software Development :: Libraries :: Python Modules
